pe_accounting_python_api/__init__.py
pe_accounting_python_api/__main__.py
pe_accounting_python_api/restclient.py
pe_accounting_python_api-0.5.6.dist-info/METADATA
pe_accounting_python_api-0.5.6.dist-info/WHEEL
pe_accounting_python_api-0.5.6.dist-info/top_level.txt
pe_accounting_python_api-0.5.6.dist-info/RECORD
