Metadata-Version: 2.1
Name: pe-accounting-python-api
Version: 0.5.6
Summary: API bindings for https://www.accounting.pe/sv/
Home-page: https://github.com/najlen/pe-accounting-python-api
Author: Daniel Nihlén
Author-email: daniel.nihlen@sdnit.se
License: MIT
Platform: UNKNOWN
Classifier: License :: OSI Approved :: MIT License
Classifier: Programming Language :: Python :: 3
Classifier: Programming Language :: Python :: 3.8
Requires-Dist: loguru
Requires-Dist: requests
